awsjar/__init__.py
awsjar/bucket.py
awsjar/exceptions.py
awsjar/jar.py
awsjar/utils.py
awsjar-0.0.5.dist-info/METADATA
awsjar-0.0.5.dist-info/RECORD
awsjar-0.0.5.dist-info/WHEEL
awsjar-0.0.5.dist-info/top_level.txt
